vexpresso/__init__.py
vexpresso/collection.py
vexpresso/create_collection.py
vexpresso/utils.py
vexpresso/daft/__init__.py
vexpresso/daft/collection.py
vexpresso/daft/filter.py
vexpresso/daft/utils.py
vexpresso/embedding_functions/__init__.py
vexpresso/embedding_functions/base.py
vexpresso/embedding_functions/clip.py
vexpresso/embedding_functions/sentence_transformers.py
vexpresso/retrievers/__init__.py
vexpresso/retrievers/base.py
vexpresso/retrievers/faiss.py
vexpresso/retrievers/np.py
vexpresso-0.0.2.dist-info/LICENSE
vexpresso-0.0.2.dist-info/METADATA
vexpresso-0.0.2.dist-info/WHEEL
vexpresso-0.0.2.dist-info/top_level.txt
vexpresso-0.0.2.dist-info/RECORD
