Metadata-Version: 2.1
Name: vexpresso
Version: 0.0.2
Author-email: Shyam Sudhakaran <shyamsnair@protonmail.com>
Requires-Python: >=3.8
License-File: LICENSE
Requires-Dist: numpy
Requires-Dist: getdaft (==0.1.5)
Requires-Dist: pandas
Requires-Dist: pyarrow
